ying/.gitignore
ying/cli.py
ying/config.py
ying/cloud_storage/__init__.py
ying/cloud_storage/list_object_count_and_bytes.py
ying/cloud_storage/query_metrics.py
ying/notify/__init__.py
ying/plog/__init__.py
ying/thirdparty/telegram.py
ying/utils/formatter.py
ying/utils/runtime.py
ying-0.3.2.dist-info/METADATA
ying-0.3.2.dist-info/WHEEL
ying-0.3.2.dist-info/entry_points.txt
ying-0.3.2.dist-info/RECORD
